f61d/Decoder.py
f61d/LOGO.py
f61d/Polynomial2.py
f61d/__init__.py
f61d/__main__.py
f61d/__version__.py
f61d/bc.py
f61d/bingdwendwen.py
f61d/blockchain.py
f61d/core.py
f61d/cry.py
f61d/date.py
f61d/lifeGame.py
f61d/nim.py
f61d/setu.py
f61d/tank.py
f61d/test.py
f61d/yinyang.py
f61d-0.7.3.dist-info/LICENSE
f61d-0.7.3.dist-info/METADATA
f61d-0.7.3.dist-info/WHEEL
f61d-0.7.3.dist-info/top_level.txt
f61d-0.7.3.dist-info/RECORD
