Metadata-Version: 2.1
Name: f61d
Version: 0.7.3
Summary: f61d NB 666
Home-page: https://github.com/AgNO3/f61d
Author: f61d
Author-email: 1743928515@qq.com
License: MIT
Classifier: License :: OSI Approved :: MIT License
Classifier: Programming Language :: Python
Classifier: Programming Language :: Python :: 3
Classifier: Programming Language :: Python :: 3.6
Classifier: Programming Language :: Python :: Implementation :: CPython
Classifier: Programming Language :: Python :: Implementation :: PyPy
Requires-Python: >=3.0.0
License-File: LICENSE
Requires-Dist: tqdm
Requires-Dist: termcolor
Requires-Dist: Pillow
Requires-Dist: requests
Requires-Dist: numpy
